{"word[0]":"pros and cons","definition[0]":"the advantages and disadvantages of something","example[0]":"We discussed the pros and cons of going to university.","note[0]":"the pros and cons of (doing) something","definition[1]":"the advantages and disadvantages of something, which you consider when making a decision about it","example[1]":"When you’re choosing a savings account, it is worthwhile spending some time weighing up the pros and cons (=thinking about them) of the various types of account on offer."}