{"word[0]":"psychology","plural[0]":"psychologies","definition[0]":"the study of the mind and how it influences people’s behaviour","example[0]":"experts in the field of developmental psychology","note[0]":"educational/social etc psychology","definition[1]":"the mental processes involved in believing in something or doing a certain activity","example[1]":"research into the psychology of racism","note[1]":"psychology of","definition[2]":"what someone thinks or believes, and how this affects what they do","example[2]":"the psychology of three-year-olds","example[3]":"mob psychology","example[4]":"You have to use psychology to get people to stop smoking."}