{"word[0]":"odd","comparative[0]":"odder","superlative[0]":"oddest","signpost[0]":"strange","definition[0]":"different from what is normal or expected, especially in a way that you disapprove of or cannot understand","example[0]":"It was an odd thing to say.","example[1]":"an odd way to behave","example[2]":"They’re an odd couple.","example[3]":"There was something odd about him.","example[4]":"What she did was unforgivable, but the odd thing was he didn’t seem to mind.","example[5]":"She was holding an extremely odd-looking weapon.","example[6]":"It seemed odd that he wanted a picture of me.","note[0]":"it is/seems odd (that)","signpost[1]":"various","definition[1]":"not specially chosen or collected","example[7]":"Any odd scrap of paper will do.","signpost[2]":"not in a pair/set","definition[2]":"separated from a pair or set","example[8]":"an odd shoe","example[9]":"He was wearing odd socks.","note[1]":"odd socks/gloves etc"}