{"word[0]":"Thursday","definition[0]":"the day between Wednesday and Friday","example[0]":"She was working Thursday. American English","example[1]":"There’s a meeting on Thursday night.","note[0]":"Thursday morning/afternoon etc","example[2]":"He was arrested last Thursday.","note[1]":"last Thursday","example[3]":"Mark and I are driving south this Thursday.","note[2]":"this Thursday","example[4]":"I’ll see you next Thursday.","note[3]":"next Thursday","example[5]":"I went to Edinburgh on Thursday.","note[4]":"on Thursday","example[6]":"Christmas Day is on a Thursday this year.","note[5]":"a Thursday"}