{"word[0]":"immersion","definition[0]":"the action of immersing something in liquid, or the state of being immersed","example[0]":"his near-fatal immersion in the icy Atlantic Ocean","note[0]":"immersion in","definition[1]":"the fact of being completely involved in something you are doing","example[1]":"my immersion in black music and culture","definition[2]":"the language teaching method in which people are put in situations where they have to use the new language","definition[3]":"an immersion heater"}