{"word[0]":"ignorant","definition[0]":"not knowing facts or information that you ought to know","example[0]":"an ignorant and uneducated man","example[1]":"Political historians are often rather ignorant of economics.","note[0]":"ignorant of","example[2]":"Many people remain blissfully ignorant about the dangers of too much sun  (=happy because they do not know about the dangers).","note[1]":"ignorant about","definition[1]":"caused by a lack of knowledge and understanding","example[3]":"an ignorant remark","example[4]":"ignorant opinions","definition[2]":"rude or impolite","example[5]":"ignorant behaviour"}