{"word[0]":"ethics","definition[0]":"moral rules or principles of behaviour for deciding what is right and wrong","example[0]":"a report on the ethics of gene therapy","example[1]":"public concern about medical ethics","note[0]":"professional/business/medical ethics","example[2]":"a code of ethics","definition[1]":"moral rules or principles of behaviour that should guide members of a profession or organization and make them deal honestly and fairly with each other and with their customers","example[3]":"Besides sales techniques, salespeople will get training in contract law, psychology, and business ethics.","example[4]":"The firm observes high standards of professional ethics.","example[5]":"a journalistic code of ethics (=list of moral rules for a particular activity or profession)"}