{"word[0]":"repel","definition[0]":"if something repels you, it is so unpleasant that you do not want to be near it, or it makes you feel ill","example[0]":"The smell repelled him.","definition[1]":"to make someone who is attacking you go away, by fighting them","example[1]":"The army was ready to repel an attack.","definition[2]":"to keep something or someone away from you","example[2]":"a lotion that repels mosquitoes","definition[3]":"if two things repel each other, they push each other away with an electrical force","opposite[0]":"attract","example[3]":"Two positive charges repel each other."}