{"word[0]":"lousy","comparative[0]":"lousier","superlative[0]":"lousiest","definition[0]":"of very bad quality","synonym[0]":"awful","example[0]":"What lousy weather!","example[1]":"The food was lousy.","example[2]":"a lousy film","definition[1]":"not very good at doing something","synonym[1]":"hopeless","example[3]":"a lousy teacher","example[4]":"I’m lousy at tennis.","note[0]":"lousy at/with","example[5]":"Brenda’s lousy with kids.","definition[2]":"small, useless, or unimportant","example[6]":"He left me a lousy fifty cent tip."}