{"word[0]":"copyright","definition[0]":"the legal right to be the only producer or seller of a book, play, film, or record for a specific length of time","note[0]":"infringement/breach of copyright (=when you break the copyright laws)","example[0]":"Who owns the copyright of this book?","example[1]":"The database will be protected by copyright.","definition[1]":"a legal right to be the only producer or seller of a book, play, film, or record for a particular length of time","example[2]":"A lecturer normally owns the copyright in any book or article he writes.","example[3]":"Drawings are prepared for most designs and drawings are protected by copyright as artistic works.","example[4]":"She started High Court proceedings against her publishing house for breach of copyright.","example[5]":"The distributer must not tamper with the content of the videos, including the copyright notice.","definition[2]":"to obtain a legal right to be the only producer or seller of a book, play, film, or record for a particular period of time","example[6]":"It’s impossible to copyright a number, as Intel has found to its cost in its failed attempts to sue rival ‘386’ chip manufacturers."}