{"word[0]":"sadly","definition[0]":"in a way that shows that you are sad","synonym[0]":"unhappily","example[0]":"Peter shook his head sadly.","definition[1]":"unfortunately","example[1]":"Sadly, the business failed.","definition[2]":"very much – used when talking about bad situations or states","example[2]":"The garden’s been sadly neglected.","example[3]":"Good restaurants were sadly lacking.","example[4]":"He was a popular man who will be sadly missed.","example[5]":"I’m afraid you’re going to be sadly disappointed.","example[6]":"If you think you’ll get any money from him, you’re sadly mistaken."}