{"word[0]":"explicit","definition[0]":"expressed in a way that is very clear and direct","example[0]":"The contrast could not have been made more explicit.","example[1]":"explicit knowledge of grammar","example[2]":"The kidnappers gave us explicit instructions not to involve the police.","example[3]":"Be explicit when you talk about money with your family.","example[4]":"He made the rules without being explicit about them.","note[0]":"explicit about","definition[1]":"language or pictures that are explicit describe or show sex or violence very clearly","example[5]":"The film contains some very explicit love scenes.","example[6]":"sexually explicit language"}