{"word[0]":"Monday","definition[0]":"the day between Sunday and Tuesday","example[0]":"Let’s go out for a meal on Monday night.","note[0]":"Monday morning/afternoon etc","example[1]":"Kelly arrived last Monday.","note[1]":"last Monday","example[2]":"The UK office will open for business this Monday.","note[2]":"this Monday","example[3]":"Shall we meet next Monday?","note[3]":"next Monday","example[4]":"It was raining on Monday.","note[4]":"on Monday","example[5]":"The president announced Monday that he would cancel the debt.","example[6]":"My birthday’s on a Monday this year.","note[5]":"a Monday"}