{"word[0]":"stub","definition[0]":"the short part of something long and thin, such as a cigarette or pencil, that is left when the rest has been used","example[0]":"a pencil stub","definition[1]":"the part of a ticket that is given back to you after it has been torn, as proof that you have paid","example[1]":"a ticket stub","definition[2]":"a piece of a cheque left in a cheque book as a record after the main part has been torn out","example[2]":"a check stub","definition[3]":"the part of something such as a cheque that you complete and keep as a record","synonym[0]":"COUNTERFOIL","example[3]":"I went through my check stubs and other records to try to find where the money had gone."}