{"word[0]":"vigorous","definition[0]":"using a lot of energy and strength or determination","example[0]":"Your dog needs at least 20 minutes of vigorous exercise every day.","example[1]":"Environmentalists have begun a vigorous campaign to oppose nuclear dumping in the area.","example[2]":"a vigorous debate","example[3]":"Vigorous efforts are being made to find a solution to the problem.","example[4]":"The measures provoked vigorous opposition in right-wing circles.","definition[1]":"strong and healthy","example[5]":"a vigorous young man"}