{"word[0]":"auto","plural[0]":"autos","definition[0]":"a car","example[0]":"imported autos","example[1]":"the auto industry","example[2]":"auto insurance","definition[1]":"of or by yourself","example[3]":"an autobiography","definition[2]":"working by itself","example[4]":"a camera with an auto-focus lens","definition[3]":"another name for AUTOMOBILE,  especially when talking about the car industry","example[5]":"auto manufacturers","example[6]":"Japan’s auto dealerships are controlled by the producers.","definition[4]":"shares in companies that make cars","example[7]":"He is avoiding airlines, autos and retailers."}